rtl/counter.v
module counter (
    input wire clk,
    input wire rst_n,
    output reg [31:0] count
);

always @(posedge clk or negedge rst_n)
    if (!rst_n)
        count <= 32'b0;
    else
        count <= count + 1'b1;
    
endmodule

tb/tb_counter.v
`timescale 2ps/1ps
module tb_counter;
reg clk;
reg rst_n;

wire [31:0] count;

counter tb_counter
(
    .rst_n (rst_n),
    .clk (clk),

    .count (count)
);

localparam CLK_PERIOD = 10;
always #(CLK_PERIOD/2) clk=~clk;

initial begin
    $dumpfile("tb_counter.vcd");
    $dumpvars(0, tb_counter);
end

initial begin
    #(CLK_PERIOD*1) rst_n<=1'bx;clk<=1'bx;
    #(CLK_PERIOD*3) rst_n<=0;
    #(CLK_PERIOD*3) rst_n<=1;clk<=0;
    #(CLK_PERIOD*100)
    rst_n<=0;
    #(CLK_PERIOD*5)
    $finish();
end

endmodule

iVerilog/vcd/tb_counter.vcd
$date
	Mon Apr 21 18:58:41 2025
$end
$version
	Icarus Verilog
$end
$timescale
	1ps
$end
$scope module tb_counter $end
$scope module tb_counter $end
$var wire 1 ! clk $end
$var wire 1 " rst_n $end
$var reg 32 # count [31:0] $end
$upscope $end
$upscope $end
$enddefinitions $end
$comment Show the parameter values. $end
$dumpall
$end
#0
$dumpvars
bx #
x"
x!
$end
#40
b0 #
0"
#70
0!
1"
#75
b1 #
1!
#80
0!
#85
b10 #
1!
#90
0!
#95
b11 #
1!
#100
0!
#105
b100 #
1!
#110
0!
#115
b101 #
1!
#120
0!
#125
b110 #
1!
#130
0!
#135
b111 #
1!
#140
0!
#145
b1000 #
1!
#150
0!
#155
b1001 #
1!
#160
0!
#165
b1010 #
1!
#170
0!
#175
b1011 #
1!
#180
0!
#185
b1100 #
1!
#190
0!
#195
b1101 #
1!
#200
0!
#205
b1110 #
1!
#210
0!
#215
b1111 #
1!
#220
0!
#225
b10000 #
1!
#230
0!
#235
b10001 #
1!
#240
0!
#245
b10010 #
1!
#250
0!
#255
b10011 #
1!
#260
0!
#265
b10100 #
1!
#270
0!
#275
b10101 #
1!
#280
0!
#285
b10110 #
1!
#290
0!
#295
b10111 #
1!
#300
0!
#305
b11000 #
1!
#310
0!
#315
b11001 #
1!
#320
0!
#325
b11010 #
1!
#330
0!
#335
b11011 #
1!
#340
0!
#345
b11100 #
1!
#350
0!
#355
b11101 #
1!
#360
0!
#365
b11110 #
1!
#370
0!
#375
b11111 #
1!
#380
0!
#385
b100000 #
1!
#390
0!
#395
b100001 #
1!
#400
0!
#405
b100010 #
1!
#410
0!
#415
b100011 #
1!
#420
0!
#425
b100100 #
1!
#430
0!
#435
b100101 #
1!
#440
0!
#445
b100110 #
1!
#450
0!
#455
b100111 #
1!
#460
0!
#465
b101000 #
1!
#470
0!
#475
b101001 #
1!
#480
0!
#485
b101010 #
1!
#490
0!
#495
b101011 #
1!
#500
0!
#505
b101100 #
1!
#510
0!
#515
b101101 #
1!
#520
0!
#525
b101110 #
1!
#530
0!
#535
b101111 #
1!
#540
0!
#545
b110000 #
1!
#550
0!
#555
b110001 #
1!
#560
0!
#565
b110010 #
1!
#570
0!
#575
b110011 #
1!
#580
0!
#585
b110100 #
1!
#590
0!
#595
b110101 #
1!
#600
0!
#605
b110110 #
1!
#610
0!
#615
b110111 #
1!
#620
0!
#625
b111000 #
1!
#630
0!
#635
b111001 #
1!
#640
0!
#645
b111010 #
1!
#650
0!
#655
b111011 #
1!
#660
0!
#665
b111100 #
1!
#670
0!
#675
b111101 #
1!
#680
0!
#685
b111110 #
1!
#690
0!
#695
b111111 #
1!
#700
0!
#705
b1000000 #
1!
#710
0!
#715
b1000001 #
1!
#720
0!
#725
b1000010 #
1!
#730
0!
#735
b1000011 #
1!
#740
0!
#745
b1000100 #
1!
#750
0!
#755
b1000101 #
1!
#760
0!
#765
b1000110 #
1!
#770
0!
#775
b1000111 #
1!
#780
0!
#785
b1001000 #
1!
#790
0!
#795
b1001001 #
1!
#800
0!
#805
b1001010 #
1!
#810
0!
#815
b1001011 #
1!
#820
0!
#825
b1001100 #
1!
#830
0!
#835
b1001101 #
1!
#840
0!
#845
b1001110 #
1!
#850
0!
#855
b1001111 #
1!
#860
0!
#865
b1010000 #
1!
#870
0!
#875
b1010001 #
1!
#880
0!
#885
b1010010 #
1!
#890
0!
#895
b1010011 #
1!
#900
0!
#905
b1010100 #
1!
#910
0!
#915
b1010101 #
1!
#920
0!
#925
b1010110 #
1!
#930
0!
#935
b1010111 #
1!
#940
0!
#945
b1011000 #
1!
#950
0!
#955
b1011001 #
1!
#960
0!
#965
b1011010 #
1!
#970
0!
#975
b1011011 #
1!
#980
0!
#985
b1011100 #
1!
#990
0!
#995
b1011101 #
1!
#1000
0!
#1005
b1011110 #
1!
#1010
0!
#1015
b1011111 #
1!
#1020
0!
#1025
b1100000 #
1!
#1030
0!
#1035
b1100001 #
1!
#1040
0!
#1045
b1100010 #
1!
#1050
0!
#1055
b1100011 #
1!
#1060
0!
#1065
b1100100 #
1!
#1070
b0 #
0"
0!
